importlib_metadata/__init__.py
importlib_metadata/_adapters.py
importlib_metadata/_collections.py
importlib_metadata/_compat.py
importlib_metadata/_functools.py
importlib_metadata/_itertools.py
importlib_metadata/_meta.py
importlib_metadata/_text.py
importlib_metadata/diagnose.py
importlib_metadata/py.typed
importlib_metadata/compat/__init__.py
importlib_metadata/compat/py311.py
importlib_metadata/compat/py39.py
importlib_metadata-8.6.0.dist-info/LICENSE
importlib_metadata-8.6.0.dist-info/METADATA
importlib_metadata-8.6.0.dist-info/WHEEL
importlib_metadata-8.6.0.dist-info/top_level.txt
importlib_metadata-8.6.0.dist-info/RECORD
